./.gitignore
./PKG-INFO
./README.ja.md
./README.md
./__init__.py
./cli.py
./config.toml.sample
./pyproject.toml
./uv.lock
./generators/__init__.py
./generators/image_generator.py
./generators/script_generator.py
./styles/__init__.py
./styles/presets.py
./ui/__init__.py
./ui/interactive.py
./utils/__init__.py
./utils/canvas.py
./utils/config.py
./utils/i18n.py
enikki-0.1.0.dist-info/METADATA
enikki-0.1.0.dist-info/WHEEL
enikki-0.1.0.dist-info/entry_points.txt
enikki-0.1.0.dist-info/RECORD
