Metadata-Version: 2.4
Name: enikki
Version: 0.1.0
Summary: A CLI tool to generate picture-diary style manga from text conversations
Project-URL: Homepage, https://github.com/kentaro/enikki
Project-URL: Documentation, https://github.com/kentaro/enikki#readme
Project-URL: Repository, https://github.com/kentaro/enikki
Project-URL: Issues, https://github.com/kentaro/enikki/issues
Author: Kentaro Kuribayashi
License-Expression: MIT
Keywords: ai,cli,comic,diary,enikki,generative-ai,manga,picture-diary
Classifier: Development Status :: 3 - Alpha
Classifier: Environment :: Console
Classifier: Intended Audience :: End Users/Desktop
Classifier: License :: OSI Approved :: MIT License
Classifier: Operating System :: OS Independent
Classifier: Programming Language :: Python :: 3
Classifier: Programming Language :: Python :: 3.10
Classifier: Programming Language :: Python :: 3.11
Classifier: Programming Language :: Python :: 3.12
Classifier: Topic :: Multimedia :: Graphics
Requires-Python: >=3.10
Requires-Dist: google-genai>=1.0.0
Requires-Dist: inquirerpy>=0.3.4
Requires-Dist: pillow>=10.0.0
Requires-Dist: rich>=13.0.0
Requires-Dist: typer>=0.9.0
Provides-Extra: dev
Requires-Dist: build>=1.0.0; extra == 'dev'
Requires-Dist: mypy>=1.0.0; extra == 'dev'
Requires-Dist: pytest-cov>=4.0.0; extra == 'dev'
Requires-Dist: pytest>=7.0.0; extra == 'dev'
Requires-Dist: ruff>=0.1.0; extra == 'dev'
Requires-Dist: twine>=5.0.0; extra == 'dev'
